aircal/__init__.py
aircal/events.py
aircal/export.py
aircal/dao/__init__.py
aircal/dao/airflow.py
aircal/dao/gcal.py
aircal-0.1.2.dist-info/LICENCE
aircal-0.1.2.dist-info/METADATA
aircal-0.1.2.dist-info/WHEEL
aircal-0.1.2.dist-info/top_level.txt
aircal-0.1.2.dist-info/RECORD
