Metadata-Version: 2.1
Name: aircal
Version: 0.1.2
Summary: Export and visualize Airflow DAG runs as events in Google calendar.
Home-page: http://github.com/domenp/aircal
Author: Domen Pogacnik
License: MIT
Platform: UNKNOWN
Classifier: Programming Language :: Python :: 3
Classifier: Development Status :: 4 - Beta
Requires-Dist: numpy
Requires-Dist: pandas
Requires-Dist: croniter
Requires-Dist: google-api-python-client
Requires-Dist: google-auth-httplib2
Requires-Dist: google-auth-oauthlib
Requires-Dist: sqlalchemy
